hvpdb_sync/__init__.py
hvpdb_sync-0.1.0.dist-info/METADATA
hvpdb_sync-0.1.0.dist-info/WHEEL
hvpdb_sync-0.1.0.dist-info/entry_points.txt
hvpdb_sync-0.1.0.dist-info/top_level.txt
hvpdb_sync-0.1.0.dist-info/RECORD
