Metadata-Version: 2.4
Name: hvpdb-sync
Version: 0.1.0
Summary: Data Import/Export Connectors for HVPDB
Requires-Dist: hvpdb
Dynamic: requires-dist
Dynamic: summary
